Metadata-Version: 1.1
Name: falcon-middlewares
Version: 1.0
Summary: Some middlewares for falcon
Home-page: UNKNOWN
Author: Laurent Evrard
Author-email: evrardlaurent77@gmail.com
License: WTFPL
Platform: UNKNOWN
Classifier: Programming Language :: Python
Classifier: Development Status :: 1 - Planning
Classifier: License :: OSI Approved
Classifier: Natural Language :: French
Classifier: Operating System :: OS Independent
Classifier: Programming Language :: Python :: 3.6
Classifier: Topic :: Communications
